{
 "actions": [],
 "creation": "2021-09-24 13:00:33.429366",
 "doctype": "DocType",
 "editable_grid": 1,
 "engine": "InnoDB",
 "field_order": [
  "supplier",
  "company"
 ],
 "fields": [
  {
   "fieldname": "supplier",
   "fieldtype": "Link",
   "in_list_view": 1,
   "label": "Supplier",
   "options": "Supplier"
  },
  {
   "fieldname": "company",
   "fieldtype": "Link",
   "in_list_view": 1,
   "label": "Company",
   "options": "Company"
  }
 ],
 "index_web_pages_for_search": 1,
 "istable": 1,
 "links": [],
 "modified": "2021-09-24 13:00:33.429366",
 "modified_by": "Administrator",
 "module": "mfi",
 "name": "Price List Supplier",
 "owner": "Administrator",
 "permissions": [],
 "sort_field": "modified",
 "sort_order": "DESC",
 "track_changes": 1
}